{
  "wounds": 12,
  "woundsMax": 12,
  "chance": 4,
  "determ": 2,
  "money": {
    "or": 10,
    "argent": 3,
    "cuivre": 0
  },
  "notes": "",
  "cet": {
    "corruption": "",
    "mutations": "",
    "etats": ""
  },
  "xp": {
    "actuelle": 100,
    "depensee": 0,
    "totale": 0
  },
  "stats": {
    "cc": {
      "init": 40,
      "avance": 0
    },
    "ct": {
      "init": 25,
      "avance": 5
    },
    "f": {
      "init": 32,
      "avance": 0
    },
    "e": {
      "init": 30,
      "avance": 0
    },
    "ini": {
      "init": 28,
      "avance": 5
    },
    "ag": {
      "init": 35,
      "avance": 10
    },
    "dex": {
      "init": 39,
      "avance": 5
    },
    "int": {
      "init": 32,
      "avance": 0
    },
    "fm": {
      "init": 26,
      "avance": 5
    },
    "soc": {
      "init": 38,
      "avance": 0
    }
  },
  "skillsBase": [
    {
      "name": "Art",
      "car": "Dex",
      "aug": 0,
      "base": 44
    },
    {
      "name": "Athlétisme",
      "car": "Ag",
      "aug": 5,
      "base": 45
    },
    {
      "name": "Calme",
      "car": "FM",
      "aug": 8,
      "base": 31
    },
    {
      "name": "Charme",
      "car": "Soc",
      "aug": 5,
      "base": 38
    },
    {
      "name": "Commandement",
      "car": "Soc",
      "aug": 0,
      "base": 38
    },
    {
      "name": "Conduite",
      "car": "Ag",
      "aug": 0,
      "base": 45
    },
    {
      "name": "Corps à Corps (Base)",
      "car": "CC",
      "aug": 3,
      "base": 40
    },
    {
      "name": "Discrétion",
      "car": "Ag",
      "aug": 0,
      "base": 45
    },
    {
      "name": "Dressage",
      "car": "FM",
      "aug": 0,
      "base": 31
    },
    {
      "name": "Escalade",
      "car": "F",
      "aug": 5,
      "base": 32
    },
    {
      "name": "Esquive",
      "car": "Ag",
      "aug": 5,
      "base": 45
    },
    {
      "name": "Intimidation",
      "car": "F",
      "aug": 0,
      "base": 32
    },
    {
      "name": "Intuition",
      "car": "Ini",
      "aug": 5,
      "base": 33
    },
    {
      "name": "Jeu",
      "car": "Int",
      "aug": 0,
      "base": 32
    },
    {
      "name": "Manipulation",
      "car": "Soc",
      "aug": 0,
      "base": 38
    },
    {
      "name": "Marchandage",
      "car": "Soc",
      "aug": 0,
      "base": 38
    },
    {
      "name": "Monter",
      "car": "Ag",
      "aug": 0,
      "base": 45
    },
    {
      "name": "Navigation",
      "car": "Ini",
      "aug": 0,
      "base": 33
    },
    {
      "name": "Perception",
      "car": "Ini",
      "aug": 5,
      "base": 33
    },
    {
      "name": "Ragot",
      "car": "Soc",
      "aug": 5,
      "base": 38
    },
    {
      "name": "Ramer",
      "car": "F",
      "aug": 0,
      "base": 32
    },
    {
      "name": "Représentation",
      "car": "Soc",
      "aug": 0,
      "base": 38
    },
    {
      "name": "Résistance à l'alcool",
      "car": "End",
      "aug": 0,
      "base": 30
    },
    {
      "name": "Résistance",
      "car": "End",
      "aug": 5,
      "base": 30
    },
    {
      "name": "Survie en extérieur",
      "car": "Int",
      "aug": 0,
      "base": 32
    }
  ],
  "skillsAdv": [
    {
      "name": "Évaluation",
      "car": "Int",
      "aug": 5,
      "carVal": 32
    },
    {
      "name": "Savoir (Reikland)",
      "car": "Int",
      "aug": 0,
      "carVal": 32
    },
    {
      "name": "Discrétion (Urbaine)",
      "car": "Ag",
      "aug": 6,
      "carVal": 45
    },
    {
      "name": "Crochetage (en cours d'acquisition)",
      "car": "Dex",
      "aug": -10,
      "carVal": 44
    },
    {
      "name": "Escamotage (en cours d'acquisition)",
      "car": "Dex",
      "aug": -10,
      "carVal": 44
    }
  ],
  "talents": [
    {
      "name": "Chat de gouttière",
      "desc": "Possible inversion des dés en Discrétion Urbaine."
    },
    {
      "name": "Criminel",
      "desc": "Statut de carrière pour revenus et impact social."
    },
    {
      "name": "Frappe assommante",
      "desc": "Pas de pénalité à localiser la tête avec arme assommante et improvisée."
    },
    {
      "name": "Fuite",
      "desc": "+1 M en fuite."
    }
  ],
  "weapons": [
    {
      "name": "Épée de Maître Artisan",
      "all": "Moyenne",
      "deg": "BF+4",
      "enc": 0,
      "attr": "+2 CC, Solide, Fiable"
    },
    {
      "name": "Dague (chef d'œuvre)",
      "all": "Très courte",
      "deg": "BF+2",
      "enc": 0,
      "attr": "+1 Dégât, Solide, Fiable"
    },
    {
      "name": "Couteaux de lancer (chef d'œuvre)",
      "all": "BFx2",
      "deg": "BF+2",
      "enc": 0,
      "attr": "+5 CT, +10 CT Surprise, Solide, Fiable"
    }
  ],
  "inventory": [
    {
      "name": "Sac à dos",
      "detail": "Porté",
      "enc": 0
    },
    {
      "name": "Pied de biche",
      "detail": "Sac à dos",
      "enc": 0
    },
    {
      "name": "Outils de voleur",
      "detail": "Sac à dos",
      "enc": 0
    },
    {
      "name": "Corde 10m",
      "detail": "Sac à dos",
      "enc": 0
    },
    {
      "name": "Cape très imperméable (chef d'œuvre)",
      "detail": "Sur soi ou sac à dos",
      "enc": 0
    },
    {
      "name": "Poison Paralysant Instantané (2 doses)",
      "detail": "Sac à dos",
      "enc": 0
    },
    {
      "name": "Poison Léthargique, en 2 rounds, pendant 4D10 min (6 doses)",
      "detail": "Sac à dos",
      "enc": 0
    }
  ],
  "armor": [
    {
      "loc": "Tête",
      "range": "01-09",
      "pa": 0
    },
    {
      "loc": "Bras droit",
      "range": "10-24",
      "pa": 1
    },
    {
      "loc": "Bras gauche",
      "range": "25-44",
      "pa": 1
    },
    {
      "loc": "Corps",
      "range": "45-79",
      "pa": 2
    },
    {
      "loc": "Jambe dr.",
      "range": "80-89",
      "pa": 0
    },
    {
      "loc": "Jambe gau.",
      "range": "90-00",
      "pa": 0
    }
  ],
  "collection": [
    {
      "name": "Montre à gousset / Baromètre en argent",
      "valReal": "15Pa",
      "valAzart": "Précieux",
      "stars": 3,
      "statut": "possédé",
      "desc": ""
    },
    {
      "name": "Médaillon avec la photo d'un jeune noble",
      "valReal": "5Pa",
      "valAzart": "Précieux",
      "stars": 3,
      "statut": "possédé",
      "desc": "Il ne sait pas qui c'est. Mais quelqu'un a pris la peine de faire graver ce visage."
    },
    {
      "name": "Bague en argent",
      "valReal": "2Pa",
      "valAzart": "A vendre",
      "stars": 1,
      "statut": "possédé",
      "desc": "Portée en public chez un Maître Artisan et quelqu'un l'a remarquée et en a complimenté l'allure."
    }
  ],
  "armorPieces": [
    {
      "name": "Veste en cuir",
      "pa": 1,
      "enc": 0,
      "pen": "",
      "attr": ""
    },
    {
      "name": "Plastron de cuir",
      "pa": 2,
      "enc": 0,
      "pen": "",
      "attr": "Points faibles"
    }
  ]
}