{
  "wounds": 19,
  "woundsMax": 19,
  "chance": 1,
  "determ": 2,
  "money": {
    "or": 0,
    "argent": 0,
    "cuivre": 0
  },
  "notes": "",
  "cet": {
    "corruption": "",
    "mutations": "",
    "etats": ""
  },
  "xp": {
    "actuelle": 0,
    "depensee": 100,
    "totale": 0
  },
  "stats": {
    "cc": {
      "init": 50,
      "avance": 5
    },
    "ct": {
      "init": 40,
      "avance": 0
    },
    "f": {
      "init": 35,
      "avance": 5
    },
    "e": {
      "init": 32,
      "avance": 10
    },
    "ini": {
      "init": 53,
      "avance": 0
    },
    "ag": {
      "init": 40,
      "avance": 0
    },
    "dex": {
      "init": 34,
      "avance": 0
    },
    "int": {
      "init": 47,
      "avance": 0
    },
    "fm": {
      "init": 35,
      "avance": 0
    },
    "soc": {
      "init": 29,
      "avance": 0
    }
  },
  "skillsBase": [
    {
      "name": "Art",
      "car": "Dex",
      "aug": 0,
      "base": 34
    },
    {
      "name": "Athlétisme",
      "car": "Ag",
      "aug": 0,
      "base": 40
    },
    {
      "name": "Calme",
      "car": "FM",
      "aug": 0,
      "base": 35
    },
    {
      "name": "Charme",
      "car": "Soc",
      "aug": 0,
      "base": 29
    },
    {
      "name": "Commandement",
      "car": "Soc",
      "aug": 0,
      "base": 29
    },
    {
      "name": "Conduite",
      "car": "Ag",
      "aug": 0,
      "base": 40
    },
    {
      "name": "Corps à Corps (Base)",
      "car": "CC",
      "aug": 3,
      "base": 55
    },
    {
      "name": "Discrétion",
      "car": "Ag",
      "aug": 0,
      "base": 40
    },
    {
      "name": "Dressage",
      "car": "FM",
      "aug": 0,
      "base": 35
    },
    {
      "name": "Escalade",
      "car": "F",
      "aug": 5,
      "base": 40
    },
    {
      "name": "Esquive",
      "car": "Ag",
      "aug": 0,
      "base": 40
    },
    {
      "name": "Intimidation",
      "car": "F",
      "aug": 0,
      "base": 40
    },
    {
      "name": "Intuition",
      "car": "Ini",
      "aug": 0,
      "base": 53
    },
    {
      "name": "Jeu",
      "car": "Int",
      "aug": 0,
      "base": 47
    },
    {
      "name": "Manipulation",
      "car": "Soc",
      "aug": 0,
      "base": 29
    },
    {
      "name": "Marchandage",
      "car": "Soc",
      "aug": 0,
      "base": 29
    },
    {
      "name": "Monter",
      "car": "Ag",
      "aug": 0,
      "base": 40
    },
    {
      "name": "Navigation",
      "car": "Ini",
      "aug": 0,
      "base": 53
    },
    {
      "name": "Perception",
      "car": "Ini",
      "aug": 10,
      "base": 53
    },
    {
      "name": "Ragot",
      "car": "Soc",
      "aug": 0,
      "base": 29
    },
    {
      "name": "Ramer",
      "car": "F",
      "aug": 0,
      "base": 40
    },
    {
      "name": "Représentation",
      "car": "Soc",
      "aug": 0,
      "base": 29
    },
    {
      "name": "Résistance à l'alcool",
      "car": "End",
      "aug": 0,
      "base": 42
    },
    {
      "name": "Résistance",
      "car": "End",
      "aug": 5,
      "base": 42
    },
    {
      "name": "Survie en extérieur",
      "car": "Int",
      "aug": 8,
      "base": 47
    }
  ],
  "skillsAdv": [
    {
      "name": "Discrétion (Rurale)",
      "car": "Ag",
      "aug": 5,
      "carVal": 40
    },
    {
      "name": "Pistage",
      "car": "Ini",
      "aug": 3,
      "carVal": 53
    },
    {
      "name": "Projectiles (Arc)",
      "car": "CT",
      "aug": 5,
      "carVal": 40
    },
    {
      "name": "Emprise sur les animaux",
      "car": "FM",
      "aug": 5,
      "carVal": 35
    },
    {
      "name": "Piégeage",
      "car": "Dex",
      "aug": 5,
      "carVal": 34
    },
    {
      "name": "Corps à corps (Arme à 2 mains)",
      "car": "CC",
      "aug": 0,
      "carVal": 55
    },
    {
      "name": "Savoir (Bêtes)",
      "car": "Int",
      "aug": 5,
      "carVal": 47
    }
  ],
  "talents": [
    {
      "name": "Dur à Cuire",
      "desc": "Gain d'autant de Points de B. que votre BE, continu et exponentiel."
    },
    {
      "name": "Bonne marcheuse (Forêt)",
      "desc": "Ignore les pénalités de ce milieu."
    },
    {
      "name": "Trappeuse",
      "desc": "+10 détection et utilisation des pièges."
    }
  ],
  "weapons": [
    {
      "name": "Épées jumelles Elfiques",
      "all": "Moyenne",
      "deg": "BF+4",
      "enc": 0,
      "attr": "Tranchantes"
    },
    {
      "name": "Dague",
      "all": "Très courte",
      "deg": "BF+2",
      "enc": 0,
      "attr": "—"
    },
    {
      "name": "Arc",
      "all": "50m",
      "deg": "BF+3",
      "enc": 0,
      "attr": "—"
    }
  ],
  "inventory": [
    {
      "name": "Besace",
      "detail": "Portée en bandoulière",
      "enc": 0
    },
    {
      "name": "Cape épaisse",
      "detail": "Sur soi ou besace",
      "enc": 0
    },
    {
      "name": "Bottes",
      "detail": "Sur soi",
      "enc": 0
    },
    {
      "name": "Assortiment de pièges à animaux",
      "detail": "Besace",
      "enc": 0
    },
    {
      "name": "Vêtements courants (forestier)",
      "detail": "Sur soi ou besace",
      "enc": 0
    }
  ],
  "armor": [
    {
      "loc": "Tête",
      "range": "01-09",
      "pa": 0
    },
    {
      "loc": "Bras droit",
      "range": "10-24",
      "pa": 1
    },
    {
      "loc": "Bras gauche",
      "range": "25-44",
      "pa": 1
    },
    {
      "loc": "Corps",
      "range": "45-79",
      "pa": 1
    },
    {
      "loc": "Jambe dr.",
      "range": "80-89",
      "pa": 0
    },
    {
      "loc": "Jambe gau.",
      "range": "90-00",
      "pa": 0
    }
  ],
  "armorPieces": [
    {
      "name": "Veste de suir",
      "pa": 1,
      "enc": 0,
      "pen": "−1 Ag",
      "attr": "Résistante, Lourde"
    }
  ]
}